README.md
setup.py
doorstopnew/__init__.py
doorstopnew/common.py
doorstopnew/settings.py
doorstopnew/cli/__init__.py
doorstopnew/cli/commands.py
doorstopnew/cli/main.py
doorstopnew/cli/utilities.py
doorstopnew/server/__init__.py
doorstopnew/server/client.py
doorstopnew/server/main.py
doorstopnew/server/utilities.py
doorstopnewone.egg-info/PKG-INFO
doorstopnewone.egg-info/SOURCES.txt
doorstopnewone.egg-info/dependency_links.txt
doorstopnewone.egg-info/top_level.txt