Metadata-Version: 1.1
Name: doorstopnewone
Version: 0.1
Summary: Updated Requirement Tool
Home-page: UNKNOWN
Author: Manoj Deshpande
Author-email: manojmsritgokak@gmail.com
License: MIT
Platform: UNKNOWN
Classifier: Development Status :: 3 - Alpha
Classifier: Intended Audience :: Developers
Classifier: Topic :: Software Development :: Build Tools
Classifier: License :: OSI Approved :: MIT License
Classifier: Programming Language :: Python :: 3
Classifier: Programming Language :: Python :: 3.4
Classifier: Programming Language :: Python :: 3.5
Classifier: Programming Language :: Python :: 3.6
